pitci/__init__.py
pitci/_version.py
pitci/base.py
pitci/checks.py
pitci/dispatchers.py
pitci/docstrings.py
pitci/helpers.py
pitci/lightgbm.py
pitci/nonconformity.py
pitci/xgboost.py
pitci-0.3.1.dist-info/LICENSE
pitci-0.3.1.dist-info/WHEEL
pitci-0.3.1.dist-info/METADATA
pitci-0.3.1.dist-info/RECORD
