Metadata-Version: 2.1
Name: pitci
Version: 0.3.1
Summary: Prediction intervals for trees using conformal intervals - pitci
Home-page: https://github.com/richardangell/pitci
Author: Richard Angell
Author-email: richardangell37@gmail.com
Requires-Python: >=3.6
Classifier: Programming Language :: Python :: 3
Classifier: License :: OSI Approved :: BSD License
Classifier: Operating System :: OS Independent
Requires-Dist: numpy>=1.9
Requires-Dist: pandas>=1.0.0
Requires-Dist: custom_inherit==2.3.1
Requires-Dist: Sphinx==3.5.4 ; extra == "doc"
Requires-Dist: sphinx-rtd-theme==0.5.2 ; extra == "doc"
Requires-Dist: numpydoc==1.1.0 ; extra == "doc"
Requires-Dist: lightgbm>=3.0.0 ; extra == "lightgbm"
Requires-Dist: pre-commit==2.11.1 ; extra == "test"
Requires-Dist: pytest==6.2.3 ; extra == "test"
Requires-Dist: pytest-cov==2.11.1 ; extra == "test"
Requires-Dist: pytest-mock==3.5.1 ; extra == "test"
Requires-Dist: black==20.8b1 ; extra == "test"
Requires-Dist: flake8==3.9.0 ; extra == "test"
Requires-Dist: bandit==1.7.0 ; extra == "test"
Requires-Dist: mypy==0.812 ; extra == "test"
Requires-Dist: scikit-learn>=0.22.1 ; extra == "test"
Requires-Dist: xgboost>=0.82 ; extra == "test"
Requires-Dist: lightgbm>=3.0.0 ; extra == "test"
Requires-Dist: xgboost>=0.82 ; extra == "xgboost"
Project-URL: Documentation, https://pitci.readthedocs.io/en/latest/
Project-URL: PyPI, https://pypi.org/project/pitci/
Provides-Extra: doc
Provides-Extra: lightgbm
Provides-Extra: test
Provides-Extra: xgboost
